jwtifypy/__init__.py
jwtifypy/config.py
jwtifypy/key.py
jwtifypy/manager.py
jwtifypy/query.py
jwtifypy/store.py
jwtifypy/utils.py
jwtifypy-0.2.1.dist-info/LICENSE
jwtifypy-0.2.1.dist-info/METADATA
jwtifypy-0.2.1.dist-info/WHEEL
jwtifypy-0.2.1.dist-info/RECORD
