Metadata-Version: 2.3
Name: jwtifypy
Version: 0.2.1
Summary: Lightweight and extensible Python library for generating and verifying JWT tokens with multiple algorithms (HS256, ES256, RS256, etc.). Built on PyJWT, it provides an intuitive interface, flexible configuration, and secure key storage.
License: MIT
Author: LordCode
Author-email: 9999269010dddd@gmail.com
Requires-Python: >=3.11,<4.0
Classifier: Development Status :: 3 - Alpha
Classifier: Framework :: FastAPI
Classifier: Intended Audience :: Developers
Classifier: License :: OSI Approved :: MIT License
Classifier: Operating System :: OS Independent
Classifier: Programming Language :: Python :: 3
Classifier: Programming Language :: Python :: 3.11
Classifier: Programming Language :: Python :: 3.12
Classifier: Programming Language :: Python :: 3.13
Classifier: Topic :: Internet :: WWW/HTTP
Classifier: Topic :: Software Development :: Libraries
Provides-Extra: crypto
Provides-Extra: env
Provides-Extra: full
Requires-Dist: cryptography (>=45.0.5,<46.0.0) ; extra == "crypto" or extra == "full"
Requires-Dist: pyjwt (>=2.10.1,<3.0.0)
Requires-Dist: python-dotenv (>=1.1.1,<2.0.0) ; extra == "env" or extra == "full"
Project-URL: Homepage, https://github.com/lordcod/jwtifypy
Project-URL: Repository, https://github.com/lordcod/jwtifypy
